admize/__init__.py
admize-0.0.1.dist-info/licenses/LICENSE.txt
admize-0.0.1.dist-info/METADATA
admize-0.0.1.dist-info/WHEEL
admize-0.0.1.dist-info/top_level.txt
admize-0.0.1.dist-info/RECORD
